LICENSE.rst
LICENSE_GPL.rst
MANIFEST.in
README.rst
setup.py
src/agx/__init__.py
src/agx.transform.uml2fs.egg-info/PKG-INFO
src/agx.transform.uml2fs.egg-info/SOURCES.txt
src/agx.transform.uml2fs.egg-info/dependency_links.txt
src/agx.transform.uml2fs.egg-info/entry_points.txt
src/agx.transform.uml2fs.egg-info/namespace_packages.txt
src/agx.transform.uml2fs.egg-info/not-zip-safe
src/agx.transform.uml2fs.egg-info/requires.txt
src/agx.transform.uml2fs.egg-info/top_level.txt
src/agx/transform/__init__.py
src/agx/transform/uml2fs/__init__.py
src/agx/transform/uml2fs/configure.zcml
src/agx/transform/uml2fs/tests.py
src/agx/transform/uml2fs/transform.py
src/agx/transform/uml2fs/transform.rst